codegeex/__init__.py
codegeex/benchmark/__init__.py
codegeex/benchmark/evaluate_humaneval_x.py
codegeex/benchmark/execution.py
codegeex/benchmark/gather_output.py
codegeex/benchmark/inspect_result.py
codegeex/benchmark/metric.py
codegeex/benchmark/utils.py
codegeex/benchmark/humaneval-x/__init__.py
codegeex/benchmark/humaneval-x/evaluate_humaneval_x.py
codegeex/benchmark/humaneval-x/generate_humaneval_x.py
codegeex/benchmark/humaneval-x/translate_humaneval_x.py
codegeex/data/__init__.py
codegeex/data/data_utils.py
codegeex/data/process_pretrain_dataset.py
codegeex/data/processor.py
codegeex/data/types.py
codegeex/kernels/__init__.py
codegeex/megatron/__init__.py
codegeex/megatron/arguments.py
codegeex/megatron/checkpointing.py
codegeex/megatron/code_generation_utils.py
codegeex/megatron/convert_ckpt_parallel.py
codegeex/megatron/enums.py
codegeex/megatron/global_vars.py
codegeex/megatron/inference.py
codegeex/megatron/initialize.py
codegeex/megatron/learning_rates.py
codegeex/megatron/memory.py
codegeex/megatron/merge_ckpt_parallel.py
codegeex/megatron/microbatches.py
codegeex/megatron/mindspore_to_megatron.py
codegeex/megatron/p2p_communication.py
codegeex/megatron/schedules.py
codegeex/megatron/training.py
codegeex/megatron/utils.py
codegeex/megatron/data/__init__.py
codegeex/megatron/data/blendable_dataset.py
codegeex/megatron/data/data_samplers.py
codegeex/megatron/data/dataset_utils.py
codegeex/megatron/data/indexed_dataset.py
codegeex/megatron/data/prompt_dataset.py
codegeex/megatron/model/__init__.py
codegeex/megatron/model/codegeex_model.py
codegeex/megatron/model/distributed.py
codegeex/megatron/model/language_model.py
codegeex/megatron/model/module.py
codegeex/megatron/model/transformer.py
codegeex/megatron/model/utils.py
codegeex/megatron/mpu/__init__.py
codegeex/megatron/mpu/cross_entropy.py
codegeex/megatron/mpu/data.py
codegeex/megatron/mpu/initialize.py
codegeex/megatron/mpu/layers.py
codegeex/megatron/mpu/mappings.py
codegeex/megatron/mpu/random.py
codegeex-1.0.dist-info/LICENSE
codegeex-1.0.dist-info/METADATA
codegeex-1.0.dist-info/WHEEL
codegeex-1.0.dist-info/top_level.txt
codegeex-1.0.dist-info/RECORD
