Metadata-Version: 2.1
Name: codegeex
Version: 1.0
Summary: CodeGeeX: A Open Multilingual Code Generation Model.
Author: Qinkai Zheng
License-File: LICENSE
Requires-Dist: fire (>=0.4.0)
Requires-Dist: ipython (>=8.4.0)
Requires-Dist: numpy (>=1.22.0)
Requires-Dist: pandas (>=1.3.5)
Requires-Dist: pyzmq (>=23.2.1)
Requires-Dist: regex (>=2022.3.15)
Requires-Dist: setuptools (>=58.0.4)
Requires-Dist: transformers (>=4.22.0)
Requires-Dist: tokenizers (>=0.11.0)
Requires-Dist: torch (>=1.10.0)
Requires-Dist: tqdm (>=4.63.0)
Requires-Dist: cpm-kernels
Requires-Dist: deepspeed (>0.6.1)
